nsapiwrapper/__init__.py
nsapiwrapper/exceptions.py
nsapiwrapper/info.py
nsapiwrapper/main.py
nsapiwrapper/objects.py
nsapiwrapper/urls.py
nsapiwrapper/utils.py
nsapiwrapper-0.0.2.dist-info/LICENSE
nsapiwrapper-0.0.2.dist-info/METADATA
nsapiwrapper-0.0.2.dist-info/WHEEL
nsapiwrapper-0.0.2.dist-info/top_level.txt
nsapiwrapper-0.0.2.dist-info/RECORD
