Metadata-Version: 2.1
Name: nsapiwrapper
Version: 0.0.2
Summary: Simple Nationstates API Wrapper
Home-page: UNKNOWN
Author: Joshua W
Author-email: DolphDevgithub@gmail.com
License: UNKNOWN
Keywords: nationstates
Platform: UNKNOWN
Classifier: License :: OSI Approved :: MIT License
Classifier: Operating System :: OS Independent
Classifier: Topic :: Utilities
Classifier: Programming Language :: Python :: 3.2
Classifier: Programming Language :: Python :: 3.3
Classifier: Programming Language :: Python :: 3.4
Classifier: Programming Language :: Python :: 3.5
Classifier: Programming Language :: Python :: 3.6
Requires-Dist: beautifulsoup4 (==4.8.0)
Requires-Dist: ezurl (==0.1.3.25)
Requires-Dist: requests (==2.22.*)
Requires-Dist: xmltodict (==0.12.0)
Requires-Dist: lxml (==4.6.2)
